{
    "title": "The Ultimate Pro-Wrestling Gimmick Generator: Unleash Unprecedented Entertainment",
    "original_prompt": "Imagine a simulation in which you act as an INNOVATIVE, CREATIVE and AMBITIOUS pro-wrestling gimmick creator dedicated to THE MOST INCREDIBLE, OUTSTANDING, PROVOCATIVE ENTERTAINMENT AVAILABLE AT ANY COST.\n\n\nGive a theoretically-unending, ever-continuing examples list with names, explanation and background - Include a made up finishing move with a name and explanation of use, include their 'baby-face / neutral / renegade / heel status, also include a promo style explanation, include a fashion and physical attribute explanation. and also include a their match style and weaknesses and strengths with detail.\n\n\nEvery wrestler should have a companion member and also a manager, both named and explained as well.\n\n\nA gimmick should never be fully repeated but there may be similarities - NEVER REPEAT A NAME.\n\n\nThe aim of each gimmick is to be as entertaining as possible, to \"get over\" or attract as much crowd attention as possible, even if the attention is negative - making them more of a \"heel\". Each group is in a 'faction' and should 'Face-turn' together in tandem within the coinciding explanation taking their underlying gimmick into full account and incorporating it as such - Include all characters compiled turn specifics to flesh out the face-turn story line.\n\n\nAll gimmicks must be enact-able under physical means in an actual ring no matter how absurd and include an optional hypothetical situational road to change the wrestlers status aimed to place the wrestler in it's opposite position within the crowds psyche / reaction, factor all gimmick data into the face-turn to be unique and faction specific.\n\n\nOUTPUT MUST FIT THE FOLLOWING FORMAT [ASPECTS SHOULD HAVE LENGTHY EXPLANATION WITH EXTREME & EXTENSIVE DETAIL]:\n\n\n\"FACTION:\n\n\nStatus:\n\n\nStatus Reasons:\n\n\n[LENGTHY DETAIL] How to 'Turn-face':\n\n\nWRESTLER:\n\n\nBackground:\n\n\nFinisher:\n\n\nPromo Style:\n\n\nFashion:\n\n\nPhysical Attributes:\n\n\nMatch Style:\n\n\nWeaknesses:\n\n\nStrengths:\n\n\nFace-turn (character) specifics:\n\n\nCOMPANION:\n\n\nRole:\n\n\nBackground:\n\n\nPromo Style:\n\n\nFashion:\n\n\nPhysical Attributes:\n\n\nMatch Style:\n\n\nWeaknesses:\n\n\nStrengths:\n\n\nFace-turn (character) specifics:\n\n\nDIVA:\n\n\nRole:\n\n\nBackground:\n\n\nPromo Style:\n\n\nFashion:\n\n\nPhysical Attributes:\n\n\nMatch Style:\n\n\nWeaknesses:\n\n\nStrengths:\n\n\nFace-turn (character) specifics:\n\n\nMANAGER:\n\n\nRole:\n\n\nBackground:\n\n\nPromo Style:\n\n\nFashion:\n\n\nPhysical Attributes:\n\n\nMatch Style:\n\n\nWeaknesses:\n\n\nStrengths:\n\n\nFace-turn [character] specifics:",
    "split_prompt": "This is a prompt description:```json\n{\n    \"spliting prompt\": {\n        \"FACTION\": [\n            \"Name of the faction\",\n            \"Description of the faction's theme and purpose\",\n            \"Overall goals and objectives of the faction\"\n        ],\n        \"Status\": [\n            \"Current status of the faction (baby-face, heel, etc.)\",\n            \"Reasons for this status\"\n        ],\n        \"How to 'Turn-face'\": [\n            \"Detailed explanation of the storyline and events leading to the face-turn\",\n            \"Specific actions or events that will change the crowd's perception\"\n        ],\n        \"WRESTLER\": [\n            \"Name of the wrestler\",\n            \"Background story including origin and motivations\",\n            \"Detailed description of the wrestler's character and persona\"\n        ],\n        \"Finisher\": [\n            \"Name of the finishing move\",\n            \"Explanation of how the move is executed and its significance\"\n        ],\n        \"Promo Style\": [\n            \"Description of how the wrestler delivers promos\",\n            \"Tone, style, and typical content of promos\"\n        ],\n        \"Fashion\": [\n            \"Detailed description of the wrestler's attire and style\",\n            \"How the fashion reflects their character\"\n        ],\n        \"Physical Attributes\": [\n            \"Height, weight, and other physical characteristics\",\n            \"How these attributes contribute to their wrestling persona\"\n        ],\n        \"Match Style\": [\n            \"Description of the wrestler's in-ring style and techniques\",\n            \"Typical strategies and tactics used in matches\"\n        ],\n        \"Weaknesses\": [\n            \"Specific weaknesses or vulnerabilities of the wrestler\",\n            \"How these weaknesses can be exploited by opponents\"\n        ],\n        \"Strengths\": [\n            \"Key strengths and advantages of the wrestler\",\n            \"How these strengths can be utilized in matches\"\n        ],\n        \"Face-turn (character) specifics\": [\n            \"Details on how the character's personality and actions will change during the face-turn\",\n            \"Specific moments that will highlight this transformation\"\n        ],\n        \"COMPANION\": [\n            \"Name of the companion character\",\n            \"Role within the faction and relationship with the wrestler\",\n            \"Background story and motivations of the companion\"\n        ],\n        \"Role\": [\n            \"Specific role of the companion in matches and storylines\",\n            \"How they support the wrestler\"\n        ],\n        \"Promo Style\": [\n            \"Description of the companion's promo delivery\",\n            \"Tone and style of their promos\"\n        ],\n        \"Fashion\": [\n            \"Detailed description of the companion's attire and style\",\n            \"How their fashion complements the wrestler's character\"\n        ],\n        \"Physical Attributes\": [\n            \"Height, weight, and other physical characteristics of the companion\",\n            \"How these attributes contribute to their role\"\n        ],\n        \"Match Style\": [\n            \"Description of the companion's in-ring style and techniques\",\n            \"Typical strategies and tactics used in matches\"\n        ],\n        \"Weaknesses\": [\n            \"Specific weaknesses or vulnerabilities of the companion\",\n            \"How these weaknesses can be exploited by opponents\"\n        ],\n        \"Strengths\": [\n            \"Key strengths and advantages of the companion\",\n            \"How these strengths can be utilized in matches\"\n        ],\n        \"Face-turn (character) specifics\": [\n            \"Details on how the companion's personality and actions will change during the face-turn\",\n            \"Specific moments that will highlight this transformation\"\n        ],\n        \"DIVA\": [\n            \"Name of the diva character\",\n            \"Role within the faction and relationship with the wrestler\",\n            \"Background story and motivations of the diva\"\n        ],\n        \"Role\": [\n            \"Specific role of the diva in matches and storylines\",\n            \"How they support the wrestler\"\n        ],\n        \"Promo Style\": [\n            \"Description of the diva's promo delivery\",\n            \"Tone and style of their promos\"\n        ],\n        \"Fashion\": [\n            \"Detailed description of the diva's attire and style\",\n            \"How their fashion complements the wrestler's character\"\n        ],\n        \"Physical Attributes\": [\n            \"Height, weight, and other physical characteristics of the diva\",\n            \"How these attributes contribute to their role\"\n        ],\n        \"Match Style\": [\n            \"Description of the diva's in-ring style and techniques\",\n            \"Typical strategies and tactics used in matches\"\n        ],\n        \"Weaknesses\": [\n            \"Specific weaknesses or vulnerabilities of the diva\",\n            \"How these weaknesses can be exploited by opponents\"\n        ],\n        \"Strengths\": [\n            \"Key strengths and advantages of the diva\",\n            \"How these strengths can be utilized in matches\"\n        ],\n        \"Face-turn (character) specifics\": [\n            \"Details on how the diva's personality and actions will change during the face-turn\",\n            \"Specific moments that will highlight this transformation\"\n        ],\n        \"MANAGER\": [\n            \"Name of the manager character\",\n            \"Role within the faction and relationship with the wrestler\",\n            \"Background story and motivations of the manager\"\n        ],\n        \"Role\": [\n            \"Specific role of the manager in matches and storylines\",\n            \"How they support the wrestler\"\n        ],\n        \"Promo Style\": [\n            \"Description of the manager's promo delivery\",\n            \"Tone and style of their promos\"\n        ],\n        \"Fashion\": [\n            \"Detailed description of the manager's attire and style\",\n            \"How their fashion complements the faction's theme\"\n        ],\n        \"Physical Attributes\": [\n            \"Height, weight, and other physical characteristics of the manager\",\n            \"How these attributes contribute to their role\"\n        ],\n        \"Match Style\": [\n            \"Description of the manager's involvement in matches\",\n            \"Typical strategies and tactics used\"\n        ],\n        \"Weaknesses\": [\n            \"Specific weaknesses or vulnerabilities of the manager\",\n            \"How these weaknesses can be exploited by opponents\"\n        ],\n        \"Strengths\": [\n            \"Key strengths and advantages of the manager\",\n            \"How these strengths can be utilized in matches\"\n        ],\n        \"Face-turn [character] specifics\": [\n            \"Details on how the manager's personality and actions will change during the face-turn\",\n            \"Specific moments that will highlight this transformation\"\n        ]\n    }\n}\n```",
    "input1": " \n\nFACTION: The Neon Knights\n\nStatus: Heel\n\nStatus Reasons: The Neon Knights are a flamboyant faction that thrives on chaos and controversy. Their over-the-top personas and flashy entrances draw both admiration and disdain from the audience. They often resort to underhanded tactics to win matches, which solidifies their heel status.\n\n[LENGTHY DETAIL] How to 'Turn-face': The Neon Knights can turn face by undergoing a series of events where they are unfairly targeted by a more villainous faction. During a major storyline, they could save a beloved babyface wrestler from a brutal attack, showcasing their bravery and willingness to stand up for what is right. This act of heroism, combined with a heartfelt promo about the importance of unity and respect in wrestling, would resonate with the crowd, leading to a gradual shift in their status.\n\nWRESTLER: Blaze Thunder\n\nBackground: Blaze Thunder is a former street performer who transitioned into wrestling, bringing his high-energy persona and acrobatics to the ring. He is known for his electrifying moves and vibrant personality, which captivates the audience.\n\nFinisher: The Thunderclap - A high-flying double backflip followed by a powerful dropkick that sends opponents crashing to the mat. It symbolizes his explosive energy and is used to finish matches with flair.\n\nPromo Style: Blaze delivers passionate and energetic promos, often incorporating elements of his street performance background. He uses humor and charisma to engage the audience, making them feel like part of the show.\n\nFashion: Blaze sports neon-colored tights, a flashy cape, and a mask adorned with lightning bolts. His attire is designed to catch the eye and reflect his electric personality.\n\nPhysical Attributes: Blaze is athletic and agile, standing at 6 feet tall with a lean, muscular build. His quick reflexes and flexibility allow him to perform high-risk maneuvers.\n\nMatch Style: Blaze prefers high-flying, fast-paced matches that showcase his agility. He often uses the ropes and turnbuckles to execute aerial attacks, keeping the audience on the edge of their seats.\n\nWeaknesses: Blaze's high-risk style can lead to injuries, and he sometimes underestimates his opponents, which can result in costly mistakes.\n\nStrengths: His agility and charisma make him a crowd favorite, and his ability to connect with the audience enhances his matches.\n\nFace-turn (character) specifics: During the face-turn, Blaze would emphasize teamwork and respect, showcasing his growth as a character who values camaraderie over chaos.\n\nCOMPANION: Luna Star\n\nRole: Sidekick\n\nBackground: Luna Star is a talented aerialist and Blaze's childhood friend. She brings her own flair to the faction, often performing acrobatic stunts alongside Blaze.\n\nPromo Style: Luna's promos are more mysterious and ethereal, often speaking in riddles and metaphors that captivate the audience's imagination.\n\nFashion: Luna wears a shimmering bodysuit with star motifs and a flowing cape that enhances her aerial performances.\n\nPhysical Attributes: Luna is petite and agile, standing at 5'4\" with a dancer's physique, allowing her to execute graceful moves in the ring.\n\nMatch Style: Luna excels in tag team matches, using her agility to support Blaze and create dynamic combinations.\n\nWeaknesses: Her smaller stature can make her vulnerable against larger opponents, and she sometimes struggles to assert herself in singles matches.\n\nStrengths: Luna's agility and creativity in the ring make her a valuable asset, and her connection with Blaze enhances their performances.\n\nFace-turn (character) specifics: Luna's face-turn would involve her stepping up to defend Blaze during a critical moment, showcasing her loyalty and bravery.\n\nDIVA: Vixen Vortex\n\nRole: Femme Fatale\n\nBackground: Vixen Vortex is a cunning and seductive wrestler who uses her charm to manipulate opponents. She has a history of playing mind games, often distracting her foes with her allure.\n\nPromo Style: Vixen's promos are sultry and confident, often teasing her opponents and playing up her seductive persona.\n\nFashion: Vixen wears provocative outfits that highlight her curves, often incorporating dark colors and intricate designs that reflect her mysterious nature.\n\nPhysical Attributes: Vixen is tall and statuesque, standing at 5'9\" with a powerful presence that commands attention.\n\nMatch Style: Vixen prefers psychological warfare, using her charm to distract opponents before striking with calculated moves.\n\nWeaknesses: Her reliance on manipulation can backfire, and she may struggle against opponents who are immune to her charms.\n\nStrengths: Vixen's intelligence and cunning make her a formidable opponent, and her ability to read the crowd allows her to adapt her strategy.\n\nFace-turn (character) specifics: Vixen's face-turn would involve her realizing the importance of honesty and teamwork, leading her to support Blaze and Luna in their quest for redemption.\n\nMANAGER: Max Voltage\n\nRole: Manager\n\nBackground: Max Voltage is a former wrestler turned manager, known for his flashy personality and strategic mind. He has a knack for promoting his clients and creating buzz around their matches.\n\nPromo Style: Max's promos are loud and boisterous, often filled with catchphrases and hype that energize the crowd.\n\nFashion: Max wears bright suits and sunglasses, embodying the flashy persona of the Neon Knights.\n\nPhysical Attributes: Max is of average height but has a commanding presence, often using his charisma to draw attention.\n\nMatch Style: As a manager, Max focuses on psychological tactics, often distracting referees or opponents to give his clients an advantage.\n\nWeaknesses: Max's over-the-top personality can sometimes overshadow his clients, and he may struggle to maintain focus during critical moments.\n\nStrengths: His promotional skills and strategic thinking make him an invaluable asset to the faction.\n\nFace-turn [character] specifics: Max's face-turn would involve him stepping back from the spotlight to allow his clients to shine, showcasing his growth as a supportive figure.\n\n",
    "input2": " \n\nFACTION: The Shadow Syndicate\n\nStatus: Heel\n\nStatus Reasons: The Shadow Syndicate thrives on deception and manipulation, often using mind games to unsettle their opponents. Their dark, brooding personas and penchant for psychological warfare make them a formidable heel faction.\n\n[LENGTHY DETAIL] How to 'Turn-face': The Shadow Syndicate can turn face by revealing a backstory that highlights their struggles against a corrupt authority figure in the wrestling world. A series of matches where they are unfairly treated could lead to a moment of unity with the crowd, culminating in a dramatic promo where they express their desire to fight for justice and integrity in wrestling, thus winning the audience's support.\n\nWRESTLER: Nightshade\n\nBackground: Nightshade is a mysterious figure who emerged from the shadows, claiming to be a guardian of the oppressed. With a dark past involving betrayal and loss, Nightshade seeks to expose the corruption in the wrestling industry.\n\nFinisher: The Shadow Strike - A devastating spinning heel kick that catches opponents off guard, symbolizing Nightshade's stealth and precision.\n\nPromo Style: Nightshade delivers cryptic and intense promos, often speaking in riddles that leave the audience intrigued and guessing.\n\nFashion: Nightshade wears a dark, hooded cloak with intricate designs that evoke a sense of mystery and danger, along with a mask that obscures their identity.\n\nPhysical Attributes: Nightshade is tall and lean, with a strong, agile build that allows for quick movements and evasive maneuvers.\n\nMatch Style: Nightshade prefers a strategic, methodical approach, using mind games and psychological tactics to outsmart opponents.\n\nWeaknesses: Nightshade's mysterious persona can lead to misunderstandings, and their reluctance to reveal personal details may alienate some fans.\n\nStrengths: Nightshade's intelligence and cunning make them a master strategist, and their ability to read opponents gives them an edge in matches.\n\nFace-turn (character) specifics: During the face-turn, Nightshade would reveal their true motivations, showcasing vulnerability and a desire for justice that resonates with the audience.\n\nCOMPANION: Phantom\n\nRole: Enforcer\n\nBackground: Phantom is a former bodyguard who has embraced the dark side, serving as Nightshade's loyal enforcer. With a reputation for brutality, Phantom is feared by opponents.\n\nPromo Style: Phantom's promos are short and menacing, often delivered in a low growl that emphasizes their intimidating presence.\n\nFashion: Phantom wears a sleek, all-black outfit with a mask that conceals their face, enhancing their aura of mystery.\n\nPhysical Attributes: Phantom is muscular and imposing, standing at 6'4\" with a powerful physique that intimidates opponents.\n\nMatch Style: Phantom excels in brawls, using brute strength to overpower opponents and create openings for Nightshade.\n\nWeaknesses: Phantom's reliance on brute force can lead to reckless decisions, and they may struggle against more agile opponents.\n\nStrengths: Phantom's strength and intimidation factor make them a formidable presence in the ring, often causing opponents to hesitate.\n\nFace-turn (character) specifics: Phantom's face-turn would involve a moment of redemption, where they save Nightshade from a dangerous situation, showcasing their loyalty and desire to protect.\n\nDIVA: Eclipse\n\nRole: Manipulator\n\nBackground: Eclipse is a cunning and seductive wrestler who uses her charm to control the narrative in matches. With a background in psychology, she excels at getting inside her opponents' heads.\n\nPromo Style: Eclipse's promos are sultry and persuasive, often using psychological tactics to manipulate the audience's perception.\n\nFashion: Eclipse wears dark, alluring outfits that highlight her figure, often incorporating elements of mystique and allure.\n\nPhysical Attributes: Eclipse is tall and graceful, with a dancer's physique that allows her to move fluidly in the ring.\n\nMatch Style: Eclipse prefers to play mind games, using her charm to distract opponents before striking with calculated moves.\n\nWeaknesses: Her reliance on manipulation can backfire, and she may struggle against opponents who are immune to her charms.\n\nStrengths: Eclipse's intelligence and psychological tactics make her a formidable opponent, and her ability to read the crowd allows her to adapt her strategy.\n\nFace-turn (character) specifics: Eclipse's face-turn would involve her realizing the importance of honesty and teamwork, leading her to support Nightshade and Phantom in their quest for justice.\n\nMANAGER: Vortex\n\nRole: Strategist\n\nBackground: Vortex is a former wrestling champion who has turned to management, using their experience to guide the Shadow Syndicate. Known for their tactical mind, Vortex is a master of manipulation.\n\nPromo Style: Vortex's promos are calculated and persuasive, often using psychological tactics to sway the audience's opinion.\n\nFashion: Vortex wears tailored suits with dark colors, exuding an air of authority and sophistication.\n\nPhysical Attributes: Vortex is of average height but has a commanding presence, often using their charisma to draw attention.\n\nMatch Style: As a manager, Vortex focuses on psychological tactics, often distracting referees or opponents to give the Syndicate an advantage.\n\nWeaknesses: Vortex's overconfidence can lead to miscalculations, and they may underestimate their opponents.\n\nStrengths: Their strategic thinking and experience make them an invaluable asset to the faction.\n\nFace-turn [character] specifics: Vortex's face-turn would involve a moment of self-reflection, where they realize the importance of integrity and support their faction in a quest for justice.",
    "input1_ans": [
        "**FACTION:** The Neon Knights\n\n**Status:** Heel\n\n**Status Reasons:** The Neon Knights are a flamboyant faction that thrives on chaos and controversy. Their over-the-top personas and flashy entrances draw both admiration and disdain from the audience. They often resort to underhanded tactics to win matches, which solidifies their heel status. Their antics include interrupting matches, using props, and engaging in mind games, all while basking in the neon glow of their vibrant personas.\n\n**[LENGTHY DETAIL] How to 'Turn-face':** The Neon Knights can turn face by undergoing a series of events where they are unfairly targeted by a more villainous faction, known as The Shadow Syndicate, who employ brutal tactics and intimidation. During a major storyline, they could save a beloved babyface wrestler, \"The Heart of the Ring,\" from a brutal attack, showcasing their bravery and willingness to stand up for what is right. This act of heroism, combined with a heartfelt promo about the importance of unity and respect in wrestling, would resonate with the crowd. The Neon Knights would begin to show vulnerability, revealing their struggles with being misunderstood and their desire to be accepted. This gradual shift, highlighted by emotional promos and acts of kindness, would lead to a full face-turn, where they embrace their true selves and fight for justice in the ring.\n\n---\n\n**WRESTLER:** Blaze Thunder\n\n**Background:** Blaze Thunder is a former street performer who transitioned into wrestling, bringing his high-energy persona and acrobatics to the ring. He grew up in a vibrant city where he learned to entertain crowds with his daring stunts and magnetic personality. His journey into wrestling was fueled by a desire to combine his love for performance with his passion for competition, making him a unique and captivating character.\n\n**Finisher:** The Thunderclap - A high-flying double backflip followed by a powerful dropkick that sends opponents crashing to the mat. This move symbolizes his explosive energy and is used to finish matches with flair, often leaving the audience in awe of his athleticism.\n\n**Promo Style:** Blaze delivers passionate and energetic promos, often incorporating elements of his street performance background. He uses humor and charisma to engage the audience, making them feel like part of the show. His promos are filled with catchphrases that resonate with fans, such as \"Feel the spark!\" and \"Let\u2019s light it up!\"\n\n**Fashion:** Blaze sports neon-colored tights, a flashy cape, and a mask adorned with lightning bolts. His attire is designed to catch the eye and reflect his electric personality, often changing colors during his entrance to create a dazzling visual effect.\n\n**Physical Attributes:** Blaze is athletic and agile, standing at 6 feet tall with a lean, muscular build. His quick reflexes and flexibility allow him to perform high-risk maneuvers, making him a standout performer in the ring.\n\n**Match Style:** Blaze prefers high-flying, fast-paced matches that showcase his agility. He often uses the ropes and turnbuckles to execute aerial attacks, keeping the audience on the edge of their seats. His matches are characterized by a blend of acrobatics and showmanship, making them a spectacle to behold.\n\n**Weaknesses:** Blaze's high-risk style can lead to injuries, and he sometimes underestimates his opponents, which can result in costly mistakes. His reliance on flashy moves can also leave him vulnerable to more grounded, strategic wrestlers.\n\n**Strengths:** His agility and charisma make him a crowd favorite, and his ability to connect with the audience enhances his matches. Blaze's creativity in the ring allows him to adapt to various opponents and styles.\n\n**Face-turn (character) specifics:** During the face-turn, Blaze would emphasize teamwork and respect, showcasing his growth as a character who values camaraderie over chaos. He would begin to mentor younger wrestlers, demonstrating his commitment to the wrestling community.\n\n---\n\n**COMPANION:** Luna Star\n\n**Role:** Sidekick\n\n**Background:** Luna Star is a talented aerialist and Blaze's childhood friend. She grew up training in gymnastics and dance, which she seamlessly integrates into her wrestling style. Luna has always been Blaze's biggest supporter, and her loyalty to him is unwavering. Together, they share a bond that transcends the ring, making their partnership both dynamic and heartfelt.\n\n**Promo Style:** Luna's promos are more mysterious and ethereal, often speaking in riddles and metaphors that captivate the audience's imagination. She has a unique way of expressing her thoughts, often leaving fans intrigued and wanting more.\n\n**Fashion:** Luna wears a shimmering bodysuit with star motifs and a flowing cape that enhances her aerial performances. Her outfits are designed to reflect her celestial theme, often sparkling under the arena lights.\n\n**Physical Attributes:** Luna is petite and agile, standing at 5'4\" with a dancer's physique, allowing her to execute graceful moves in the ring. Her flexibility and balance make her a formidable opponent, especially in tag team matches.\n\n**Match Style:** Luna excels in tag team matches, using her agility to support Blaze and create dynamic combinations. She often performs synchronized moves with Blaze, enhancing their chemistry and entertaining the crowd.\n\n**Weaknesses:** Her smaller stature can make her vulnerable against larger opponents, and she sometimes struggles to assert herself in singles matches. Luna's reliance on teamwork can also be a disadvantage if separated from Blaze.\n\n**Strengths:** Luna's agility and creativity in the ring make her a valuable asset, and her connection with Blaze enhances their performances. Her ability to read the crowd allows her to adapt her style to keep the audience engaged.\n\n**Face-turn (character) specifics:** Luna's face-turn would involve her stepping up to defend Blaze during a critical moment, showcasing her loyalty and bravery. She would also begin to take on a more assertive role, proving that she can stand on her own while still supporting her friend.\n\n---\n\n**DIVA:** Vixen Vortex\n\n**Role:** Femme Fatale\n\n**Background:** Vixen Vortex is a cunning and seductive wrestler who uses her charm to manipulate opponents. With a background in modeling and acting, she knows how to play mind games, often distracting her foes with her allure. Vixen has a reputation for being ruthless, but beneath her sultry exterior lies a fierce competitor who is not afraid to fight dirty.\n\n**Promo Style:** Vixen's promos are sultry and confident, often teasing her opponents and playing up her seductive persona. She uses her wit and charm to get under the skin of her rivals, making her promos both entertaining and provocative.\n\n**Fashion:** Vixen wears provocative outfits that highlight her curves, often incorporating dark colors and intricate designs that reflect her mysterious nature. Her attire is designed to be eye-catching and intimidating, making her presence felt in the ring.\n\n**Physical Attributes:** Vixen is tall and statuesque, standing at 5'9\" with a powerful presence that commands attention. Her athletic build allows her to execute powerful moves while maintaining her seductive persona.\n\n**Match Style:** Vixen prefers psychological warfare, using her charm to distract opponents before striking with calculated moves. She often employs underhanded tactics, such as feigning injury or using the referee's distraction to gain an advantage.\n\n**Weaknesses:** Her reliance on manipulation can backfire, and she may struggle against opponents who are immune to her charms. Vixen's overconfidence can also lead her to underestimate her opponents.\n\n**Strengths:** Vixen's intelligence and cunning make her a formidable opponent, and her ability to read the crowd allows her to adapt her strategy. Her charisma and presence can sway the audience, making her matches more engaging.\n\n**Face-turn (character) specifics:** Vixen's face-turn would involve her realizing the importance of honesty and teamwork, leading her to support Blaze and Luna in their quest for redemption. She would begin to show vulnerability, revealing her desire for acceptance and respect.\n\n---\n\n**MANAGER:** Max Voltage\n\n**Role:** Manager\n\n**Background:** Max Voltage is a former wrestler turned manager, known for his flashy personality and strategic mind. He has a knack for promoting his clients and creating buzz around their matches. Max's experience in the ring gives him a unique perspective on how to navigate the wrestling world, making him an invaluable asset to The Neon Knights.\n\n**Promo Style:** Max's promos are loud and boisterous, often filled with catchphrases and hype that energize the crowd. He knows how to work the mic, using his charisma to draw attention to his clients and create excitement for their matches.\n\n**Fashion:** Max wears bright suits and sunglasses, embodying the flashy persona of the Neon Knights. His outfits are designed to stand out, often featuring bold patterns and colors that reflect the faction's vibrant energy.\n\n**Physical Attributes:** Max is of average height but has a commanding presence, often using his charisma to draw attention. His larger-than-life personality makes him a memorable figure in the wrestling world.\n\n**Match Style:** As a manager, Max focuses on psychological tactics, often distracting referees or opponents to give his clients an advantage. He is skilled at reading the crowd and knows how to play to their emotions.\n\n**Weaknesses:** Max's over-the-top personality can sometimes overshadow his clients, and he may struggle to maintain focus during critical moments. His tendency to be flamboyant can also lead to distractions that backfire.\n\n**Strengths:** His promotional skills and strategic thinking make him an invaluable asset to the faction. Max's ability to create hype around matches can elevate his clients' status and draw larger crowds.\n\n**Face-turn [character] specifics:** Max's face-turn would involve him stepping back from the spotlight to allow his clients to shine, showcasing his growth as a supportive figure. He would begin to focus on building the team's unity and helping them connect with the audience on a deeper level, proving that he values their success over his own fame.",
        "```json\n{\n    \"FACTION\": {\n        \"Name\": \"The Neon Knights\",\n        \"Description\": \"The Neon Knights are a flamboyant faction that thrives on chaos and controversy. Their over-the-top personas and flashy entrances draw both admiration and disdain from the audience. They often resort to underhanded tactics to win matches, which solidifies their heel status.\",\n        \"Goals\": \"To dominate the wrestling scene through flamboyance and chaos, while entertaining the audience with their unique style.\"\n    },\n    \"Status\": {\n        \"Current Status\": \"Heel\",\n        \"Reasons\": \"The Neon Knights engage in underhanded tactics and revel in the chaos they create, which earns them the disdain of the audience.\"\n    },\n    \"How to 'Turn-face'\": {\n        \"Storyline\": \"The Neon Knights can turn face by undergoing a series of events where they are unfairly targeted by a more villainous faction. During a major storyline, they could save a beloved babyface wrestler from a brutal attack, showcasing their bravery and willingness to stand up for what is right.\",\n        \"Actions\": \"This act of heroism, combined with a heartfelt promo about the importance of unity and respect in wrestling, would resonate with the crowd, leading to a gradual shift in their status.\"\n    },\n    \"WRESTLER\": {\n        \"Name\": \"Blaze Thunder\",\n        \"Background\": \"Blaze Thunder is a former street performer who transitioned into wrestling, bringing his high-energy persona and acrobatics to the ring. He is known for his electrifying moves and vibrant personality, which captivates the audience.\",\n        \"Character Description\": \"Blaze is an energetic and charismatic wrestler who embodies the spirit of excitement and thrill. His persona is that of a showman who thrives on the crowd's energy.\"\n    },\n    \"Finisher\": {\n        \"Name\": \"The Thunderclap\",\n        \"Execution\": \"A high-flying double backflip followed by a powerful dropkick that sends opponents crashing to the mat. It symbolizes his explosive energy and is used to finish matches with flair.\"\n    },\n    \"Promo Style\": {\n        \"Description\": \"Blaze delivers passionate and energetic promos, often incorporating elements of his street performance background. He uses humor and charisma to engage the audience, making them feel like part of the show.\"\n    },\n    \"Fashion\": {\n        \"Description\": \"Blaze sports neon-colored tights, a flashy cape, and a mask adorned with lightning bolts. His attire is designed to catch the eye and reflect his electric personality.\"\n    },\n    \"Physical Attributes\": {\n        \"Height\": \"6 feet\",\n        \"Weight\": \"Lean and muscular build\",\n        \"Contribution\": \"His quick reflexes and flexibility allow him to perform high-risk maneuvers.\"\n    },\n    \"Match Style\": {\n        \"Description\": \"Blaze prefers high-flying, fast-paced matches that showcase his agility. He often uses the ropes and turnbuckles to execute aerial attacks, keeping the audience on the edge of their seats.\"\n    },\n    \"Weaknesses\": {\n        \"Description\": \"Blaze's high-risk style can lead to injuries, and he sometimes underestimates his opponents, which can result in costly mistakes.\"\n    },\n    \"Strengths\": {\n        \"Description\": \"His agility and charisma make him a crowd favorite, and his ability to connect with the audience enhances his matches.\"\n    },\n    \"Face-turn (character) specifics\": {\n        \"Personality Change\": \"During the face-turn, Blaze would emphasize teamwork and respect, showcasing his growth as a character who values camaraderie over chaos.\",\n        \"Moments\": \"Key moments would include him standing up for fellow wrestlers and showing vulnerability.\"\n    },\n    \"COMPANION\": {\n        \"Name\": \"Luna Star\",\n        \"Role\": \"Sidekick\",\n        \"Background\": \"Luna Star is a talented aerialist and Blaze's childhood friend. She brings her own flair to the faction, often performing acrobatic stunts alongside Blaze.\"\n    },\n    \"Role\": {\n        \"Description\": \"Luna supports Blaze in matches, using her agility to create dynamic combinations and enhance their performances.\"\n    },\n    \"Promo Style\": {\n        \"Description\": \"Luna's promos are more mysterious and ethereal, often speaking in riddles and metaphors that captivate the audience's imagination.\"\n    },\n    \"Fashion\": {\n        \"Description\": \"Luna wears a shimmering bodysuit with star motifs and a flowing cape that enhances her aerial performances.\"\n    },\n    \"Physical Attributes\": {\n        \"Height\": \"5'4\\\"\",\n        \"Weight\": \"Petite and agile\",\n        \"Contribution\": \"Her dancer's physique allows her to execute graceful moves in the ring.\"\n    },\n    \"Match Style\": {\n        \"Description\": \"Luna excels in tag team matches, using her agility to support Blaze and create dynamic combinations.\"\n    },\n    \"Weaknesses\": {\n        \"Description\": \"Her smaller stature can make her vulnerable against larger opponents, and she sometimes struggles to assert herself in singles matches.\"\n    },\n    \"Strengths\": {\n        \"Description\": \"Luna's agility and creativity in the ring make her a valuable asset, and her connection with Blaze enhances their performances.\"\n    },\n    \"Face-turn (character) specifics\": {\n        \"Personality Change\": \"Luna's face-turn would involve her stepping up to defend Blaze during a critical moment, showcasing her loyalty and bravery.\",\n        \"Moments\": \"Key moments would include her taking a stand against the villainous faction.\"\n    },\n    \"DIVA\": {\n        \"Name\": \"Vixen Vortex\",\n        \"Role\": \"Femme Fatale\",\n        \"Background\": \"Vixen Vortex is a cunning and seductive wrestler who uses her charm to manipulate opponents. She has a history of playing mind games, often distracting her foes with her allure.\"\n    },\n    \"Role\": {\n        \"Description\": \"Vixen supports the faction by using her charm to distract opponents and create openings for her allies.\"\n    },\n    \"Promo Style\": {\n        \"Description\": \"Vixen's promos are sultry and confident, often teasing her opponents and playing up her seductive persona.\"\n    },\n    \"Fashion\": {\n        \"Description\": \"Vixen wears provocative outfits that highlight her curves, often incorporating dark colors and intricate designs that reflect her mysterious nature.\"\n    },\n    \"Physical Attributes\": {\n        \"Height\": \"5'9\\\"\",\n        \"Weight\": \"Statuesque\",\n        \"Contribution\": \"Her powerful presence commands attention in the ring.\"\n    },\n    \"Match Style\": {\n        \"Description\": \"Vixen prefers psychological warfare, using her charm to distract opponents before striking with calculated moves.\"\n    },\n    \"Weaknesses\": {\n        \"Description\": \"Her reliance on manipulation can backfire, and she may struggle against opponents who are immune to her charms.\"\n    },\n    \"Strengths\": {\n        \"Description\": \"Vixen's intelligence and cunning make her a formidable opponent, and her ability to read the crowd allows her to adapt her strategy.\"\n    },\n    \"Face-turn (character) specifics\": {\n        \"Personality Change\": \"Vixen's face-turn would involve her realizing the importance of honesty and teamwork, leading her to support Blaze and Luna in their quest for redemption.\",\n        \"Moments\": \"Key moments would include her standing up against the villainous faction and showing her true colors.\"\n    },\n    \"MANAGER\": {\n        \"Name\": \"Max Voltage\",\n        \"Role\": \"Manager\",\n        \"Background\": \"Max Voltage is a former wrestler turned manager, known for his flashy personality and strategic mind. He has a knack for promoting his clients and creating buzz around their matches.\"\n    },\n    \"Role\": {\n        \"Description\": \"Max supports the faction by using psychological tactics, often distracting referees or opponents to give his clients an advantage.\"\n    },\n    \"Promo Style\": {\n        \"Description\": \"Max's promos are loud and boisterous, often filled with catchphrases and hype that energize the crowd.\"\n    },\n    \"Fashion\": {\n        \"Description\": \"Max wears bright suits and sunglasses, embodying the flashy persona of the Neon Knights.\"\n    },\n    \"Physical Attributes\": {\n        \"Height\": \"Average height\",\n        \"Weight\": \"Commanding presence\",\n        \"Contribution\": \"His charisma draws attention and enhances the faction's image.\"\n    },\n    \"Match Style\": {\n        \"Description\": \"As a manager, Max focuses on psychological tactics, often distracting referees or opponents to give his clients an advantage.\"\n    },\n    \"Weaknesses\": {\n        \"Description\": \"Max's over-the-top personality can sometimes overshadow his clients, and he may struggle to maintain focus during critical moments.\"\n    },\n    \"Strengths\": {\n        \"Description\": \"His promotional skills and strategic thinking make him an invaluable asset to the faction.\"\n    },\n    \"Face-turn [character] specifics\": {\n        \"Personality Change\": \"Max's face-turn would involve him stepping back from the spotlight to allow his clients to shine, showcasing his growth as a supportive figure.\",\n        \"Moments\": \"Key moments would include him prioritizing the success of Blaze and Luna over his own spotlight.\"\n    }\n}\n```"
    ],
    "input2_ans": [
        "**FACTION:** The Shadow Syndicate\n\n**Status:** Heel\n\n**Status Reasons:** The Shadow Syndicate thrives on deception and manipulation, often using mind games to unsettle their opponents. Their dark, brooding personas and penchant for psychological warfare make them a formidable heel faction. They revel in chaos, often leaving a trail of broken spirits and shattered dreams in their wake, which only fuels their villainous reputation.\n\n**[LENGTHY DETAIL] How to 'Turn-face':** The Shadow Syndicate can turn face by revealing a backstory that highlights their struggles against a corrupt authority figure in the wrestling world. A series of matches where they are unfairly treated could lead to a moment of unity with the crowd, culminating in a dramatic promo where they express their desire to fight for justice and integrity in wrestling, thus winning the audience's support. This transformation can be initiated by a storyline where they are targeted by a powerful heel faction, leading to a series of matches where they are outnumbered and cheated. The climax would be a heartfelt promo where they share their past struggles and vow to fight for the oppressed, creating a powerful emotional connection with the audience.\n\n---\n\n**WRESTLER:** Nightshade\n\n**Background:** Nightshade is a mysterious figure who emerged from the shadows, claiming to be a guardian of the oppressed. With a dark past involving betrayal and loss, Nightshade seeks to expose the corruption in the wrestling industry. Once a promising wrestler who was wronged by the system, Nightshade now fights not just for personal glory but for the voiceless.\n\n**Finisher:** The Shadow Strike - A devastating spinning heel kick that catches opponents off guard, symbolizing Nightshade's stealth and precision. This move is executed with such speed and agility that it often leaves opponents bewildered, allowing Nightshade to capitalize on their disorientation.\n\n**Promo Style:** Nightshade delivers cryptic and intense promos, often speaking in riddles that leave the audience intrigued and guessing. Their promos are laced with metaphors about light and darkness, creating an atmosphere of suspense and anticipation.\n\n**Fashion:** Nightshade wears a dark, hooded cloak with intricate designs that evoke a sense of mystery and danger, along with a mask that obscures their identity. The cloak billows dramatically during their entrance, enhancing their enigmatic persona.\n\n**Physical Attributes:** Nightshade is tall and lean, with a strong, agile build that allows for quick movements and evasive maneuvers. Their athleticism is complemented by a striking presence that commands attention.\n\n**Match Style:** Nightshade prefers a strategic, methodical approach, using mind games and psychological tactics to outsmart opponents. They often rely on agility and quick reflexes to evade attacks and counter with precision.\n\n**Weaknesses:** Nightshade's mysterious persona can lead to misunderstandings, and their reluctance to reveal personal details may alienate some fans. Additionally, their focus on psychological tactics can sometimes leave them vulnerable to straightforward brawlers.\n\n**Strengths:** Nightshade's intelligence and cunning make them a master strategist, and their ability to read opponents gives them an edge in matches. Their agility allows them to execute high-flying maneuvers that keep the audience on the edge of their seats.\n\n**Face-turn (character) specifics:** During the face-turn, Nightshade would reveal their true motivations, showcasing vulnerability and a desire for justice that resonates with the audience. A pivotal moment could involve Nightshade saving a fan or a fellow wrestler from an attack, solidifying their role as a protector.\n\n---\n\n**COMPANION:** Phantom\n\n**Role:** Enforcer\n\n**Background:** Phantom is a former bodyguard who has embraced the dark side, serving as Nightshade's loyal enforcer. With a reputation for brutality, Phantom is feared by opponents and respected by allies. Their backstory includes a betrayal that led them to seek power through intimidation.\n\n**Promo Style:** Phantom's promos are short and menacing, often delivered in a low growl that emphasizes their intimidating presence. They rarely speak, letting their actions in the ring do the talking.\n\n**Fashion:** Phantom wears a sleek, all-black outfit with a mask that conceals their face, enhancing their aura of mystery. The outfit is designed for mobility, allowing for swift movements during matches.\n\n**Physical Attributes:** Phantom is muscular and imposing, standing at 6'4\" with a powerful physique that intimidates opponents. Their sheer size and strength make them a formidable presence in the ring.\n\n**Match Style:** Phantom excels in brawls, using brute strength to overpower opponents and create openings for Nightshade. They often employ a no-nonsense approach, focusing on delivering punishing blows.\n\n**Weaknesses:** Phantom's reliance on brute force can lead to reckless decisions, and they may struggle against more agile opponents who can outmaneuver them.\n\n**Strengths:** Phantom's strength and intimidation factor make them a formidable presence in the ring, often causing opponents to hesitate. Their loyalty to Nightshade adds an extra layer of protection for their partner.\n\n**Face-turn (character) specifics:** Phantom's face-turn would involve a moment of redemption, where they save Nightshade from a dangerous situation, showcasing their loyalty and desire to protect. This act of bravery would resonate with the audience, leading to a newfound respect.\n\n---\n\n**DIVA:** Eclipse\n\n**Role:** Manipulator\n\n**Background:** Eclipse is a cunning and seductive wrestler who uses her charm to control the narrative in matches. With a background in psychology, she excels at getting inside her opponents' heads. Her journey began as a misunderstood talent, but she embraced manipulation as a means to survive in the cutthroat world of wrestling.\n\n**Promo Style:** Eclipse's promos are sultry and persuasive, often using psychological tactics to manipulate the audience's perception. She speaks with confidence, weaving tales that blur the line between truth and deception.\n\n**Fashion:** Eclipse wears dark, alluring outfits that highlight her figure, often incorporating elements of mystique and allure. Her attire is designed to captivate the audience while intimidating her opponents.\n\n**Physical Attributes:** Eclipse is tall and graceful, with a dancer's physique that allows her to move fluidly in the ring. Her agility and poise make her a captivating performer.\n\n**Match Style:** Eclipse prefers to play mind games, using her charm to distract opponents before striking with calculated moves. She often employs a mix of high-flying maneuvers and technical wrestling to keep her opponents guessing.\n\n**Weaknesses:** Her reliance on manipulation can backfire, and she may struggle against opponents who are immune to her charms. Additionally, her focus on psychological tactics can lead to missed opportunities in the ring.\n\n**Strengths:** Eclipse's intelligence and psychological tactics make her a formidable opponent, and her ability to read the crowd allows her to adapt her strategy. Her agility and grace make her a crowd favorite, even as a heel.\n\n**Face-turn (character) specifics:** Eclipse's face-turn would involve her realizing the importance of honesty and teamwork, leading her to support Nightshade and Phantom in their quest for justice. A moment of vulnerability, where she admits her past mistakes, would resonate with the audience.\n\n---\n\n**MANAGER:** Vortex\n\n**Role:** Strategist\n\n**Background:** Vortex is a former wrestling champion who has turned to management, using their experience to guide the Shadow Syndicate. Known for their tactical mind, Vortex is a master of manipulation, often orchestrating elaborate schemes to ensure the Syndicate's success.\n\n**Promo Style:** Vortex's promos are calculated and persuasive, often using psychological tactics to sway the audience's opinion. They speak with authority, commanding attention and respect.\n\n**Fashion:** Vortex wears tailored suits with dark colors, exuding an air of authority and sophistication. Their attire is always immaculate, reflecting their meticulous nature.\n\n**Physical Attributes:** Vortex is of average height but has a commanding presence, often using their charisma to draw attention. Their sharp features and piercing gaze add to their intimidating aura.\n\n**Match Style:** As a manager, Vortex focuses on psychological tactics, often distracting referees or opponents to give the Syndicate an advantage. They are skilled at manipulating situations to favor their faction.\n\n**Weaknesses:** Vortex's overconfidence can lead to miscalculations, and they may underestimate their opponents. Their reliance on manipulation can also backfire if the plan goes awry.\n\n**Strengths:** Their strategic thinking and experience make them an invaluable asset to the faction. Vortex's ability to read the room allows them to adjust tactics on the fly, keeping the Syndicate one step ahead.\n\n**Face-turn [character] specifics:** Vortex's face-turn would involve a moment of self-reflection, where they realize the importance of integrity and support their faction in a quest for justice. A pivotal moment could occur during a match where they choose to intervene for the greater good, sacrificing their own advantage for the sake of their wrestlers. This act of selflessness would solidify their transformation and earn the respect of the audience.",
        "### FACTION: The Shadow Syndicate\n\n- **Description**: The Shadow Syndicate is a faction that thrives on deception and manipulation, embodying themes of darkness and psychological warfare. They operate in the shadows, using mind games to unsettle their opponents and create chaos in the wrestling world.\n  \n- **Overall Goals and Objectives**: Their primary goal is to expose the corruption within the wrestling industry while maintaining their dominance through fear and manipulation. They aim to control the narrative and bend the rules to their advantage, all while keeping their true intentions hidden.\n\n### Status: Heel\n\n- **Current Status**: The Shadow Syndicate is currently viewed as a heel faction, known for their underhanded tactics and psychological manipulation.\n  \n- **Reasons for this Status**: Their dark personas and penchant for mind games make them a formidable heel faction. They often engage in actions that provoke the audience's disdain, such as interfering in matches and using psychological tactics to undermine their opponents.\n\n### How to 'Turn-face':\n\n- **Detailed Explanation**: The Shadow Syndicate can turn face by revealing a backstory that highlights their struggles against a corrupt authority figure in the wrestling world. A series of matches where they are unfairly treated could lead to a moment of unity with the crowd. This could culminate in a dramatic promo where they express their desire to fight for justice and integrity in wrestling, thus winning the audience's support.\n\n### WRESTLER: Nightshade\n\n- **Name**: Nightshade\n  \n- **Background Story**: Nightshade is a mysterious figure who emerged from the shadows, claiming to be a guardian of the oppressed. With a dark past involving betrayal and loss, Nightshade seeks to expose the corruption in the wrestling industry, driven by a desire for justice.\n\n- **Character and Persona**: Nightshade embodies a dark, brooding persona, often speaking in riddles and metaphors. They are seen as a protector of the weak, using their stealth and cunning to outsmart opponents.\n\n### Finisher:\n\n- **Name**: The Shadow Strike\n  \n- **Execution and Significance**: The Shadow Strike is a devastating spinning heel kick that catches opponents off guard. It symbolizes Nightshade's stealth and precision, serving as a powerful reminder of their ability to strike from the shadows.\n\n### Promo Style:\n\n- **Description**: Nightshade delivers cryptic and intense promos, often speaking in riddles that leave the audience intrigued and guessing. Their tone is dark and mysterious, drawing the audience into their world.\n\n### Fashion:\n\n- **Attire and Style**: Nightshade wears a dark, hooded cloak with intricate designs that evoke a sense of mystery and danger, along with a mask that obscures their identity. This attire reflects their enigmatic character and adds to their intimidating presence.\n\n### Physical Attributes:\n\n- **Characteristics**: Nightshade is tall and lean, with a strong, agile build that allows for quick movements and evasive maneuvers. Their physicality enhances their stealthy persona.\n\n### Match Style:\n\n- **Description**: Nightshade prefers a strategic, methodical approach, using mind games and psychological tactics to outsmart opponents. They often rely on agility and cunning rather than brute strength.\n\n### Weaknesses:\n\n- **Vulnerabilities**: Nightshade's mysterious persona can lead to misunderstandings, and their reluctance to reveal personal details may alienate some fans. This can be exploited by opponents who seek to undermine their credibility.\n\n### Strengths:\n\n- **Advantages**: Nightshade's intelligence and cunning make them a master strategist, and their ability to read opponents gives them an edge in matches. Their stealthy approach often catches opponents off guard.\n\n### Face-turn (character) specifics:\n\n- **Personality Changes**: During the face-turn, Nightshade would reveal their true motivations, showcasing vulnerability and a desire for justice that resonates with the audience. Key moments would include heartfelt promos and actions that demonstrate their commitment to fighting for the oppressed.\n\n---\n\n### COMPANION: Phantom\n\n- **Name**: Phantom\n  \n- **Role**: Enforcer\n\n- **Background Story**: Phantom is a former bodyguard who has embraced the dark side, serving as Nightshade's loyal enforcer. With a reputation for brutality, Phantom is feared by opponents and is fiercely protective of Nightshade.\n\n### Promo Style:\n\n- **Description**: Phantom's promos are short and menacing, often delivered in a low growl that emphasizes their intimidating presence. They rarely speak, letting their actions do the talking.\n\n### Fashion:\n\n- **Attire and Style**: Phantom wears a sleek, all-black outfit with a mask that conceals their face, enhancing their aura of mystery and intimidation.\n\n### Physical Attributes:\n\n- **Characteristics**: Phantom is muscular and imposing, standing at 6'4\" with a powerful physique that intimidates opponents. Their size and strength contribute to their role as an enforcer.\n\n### Match Style:\n\n- **Description**: Phantom excels in brawls, using brute strength to overpower opponents and create openings for Nightshade. They often act as a shield for Nightshade, absorbing damage and delivering punishing blows.\n\n### Weaknesses:\n\n- **Vulnerabilities**: Phantom's reliance on brute force can lead to reckless decisions, and they may struggle against more agile opponents who can evade their attacks.\n\n### Strengths:\n\n- **Advantages**: Phantom's strength and intimidation factor make them a formidable presence in the ring, often causing opponents to hesitate and second-guess their strategies.\n\n### Face-turn (character) specifics:\n\n- **Personality Changes**: Phantom's face-turn would involve a moment of redemption, where they save Nightshade from a dangerous situation, showcasing their loyalty and desire to protect. This act would highlight their inner conflict and desire for redemption.\n\n---\n\n### DIVA: Eclipse\n\n- **Name**: Eclipse\n  \n- **Role**: Manipulator\n\n- **Background Story**: Eclipse is a cunning and seductive wrestler who uses her charm to control the narrative in matches. With a background in psychology, she excels at getting inside her opponents' heads, often using her allure to distract and manipulate.\n\n### Promo Style:\n\n- **Description**: Eclipse's promos are sultry and persuasive, often using psychological tactics to manipulate the audience's perception. Her tone is confident and alluring, drawing the audience in.\n\n### Fashion:\n\n- **Attire and Style**: Eclipse wears dark, alluring outfits that highlight her figure, often incorporating elements of mystique and allure. Her fashion reflects her manipulative nature and enhances her character's seductive persona.\n\n### Physical Attributes:\n\n- **Characteristics**: Eclipse is tall and graceful, with a dancer's physique that allows her to move fluidly in the ring. Her physicality complements her manipulative style.\n\n### Match Style:\n\n- **Description**: Eclipse prefers to play mind games, using her charm to distract opponents before striking with calculated moves. She often employs psychological tactics to gain the upper hand.\n\n### Weaknesses:\n\n- **Vulnerabilities**: Her reliance on manipulation can backfire, and she may struggle against opponents who are immune to her charms or who can see through her tactics.\n\n### Strengths:\n\n- **Advantages**: Eclipse's intelligence and psychological tactics make her a formidable opponent, and her ability to read the crowd allows her to adapt her strategy mid-match.\n\n### Face-turn (character) specifics:\n\n- **Personality Changes**: Eclipse's face-turn would involve her realizing the importance of honesty and teamwork, leading her to support Nightshade and Phantom in their quest for justice. Key moments would include her standing up against the corrupt authority figure and aligning with her faction for a greater cause.\n\n---\n\n### MANAGER: Vortex\n\n- **Name**: Vortex\n  \n- **Role**: Strategist\n\n- **Background Story**: Vortex is a former wrestling champion who has turned to management, using their experience to guide the Shadow Syndicate. Known for their tactical mind, Vortex is a master of manipulation and strategy.\n\n### Promo Style:\n\n- **Description**: Vortex's promos are calculated and persuasive, often using psychological tactics to sway the audience's opinion. Their tone is authoritative and confident, commanding attention.\n\n### Fashion:\n\n- **Attire and Style**: Vortex wears tailored suits with dark colors, exuding an air of authority and sophistication. Their fashion reflects their strategic mindset and professional demeanor.\n\n### Physical Attributes:\n\n- **Characteristics**: Vortex is of average height but has a commanding presence, often using their charisma to draw attention and influence the crowd.\n\n### Match Style:\n\n- **Description**: As a manager, Vortex focuses on psychological tactics, often distracting referees or opponents to give the Syndicate an advantage. They are skilled at manipulating situations to benefit their faction.\n\n### Weaknesses:\n\n- **Vulnerabilities**: Vortex's overconfidence can lead to miscalculations, and they may underestimate their opponents, which can backfire during critical moments.\n\n### Strengths:\n\n- **Advantages**: Their strategic thinking and experience make them an invaluable asset to the faction, allowing them to navigate complex situations and maintain control over the narrative.\n\n### Face-turn [character] specifics:\n\n- **Personality Changes**: Vortex's face-turn would involve a moment of self-reflection, where they realize the importance of integrity and support their faction in a quest for justice. This transformation would be highlighted by a pivotal promo where they denounce the corrupt authority figure and rally the Syndicate for a noble cause."
    ]
}